setup.py
ceexample/__init__.py
ceexample/command.py
ceexample.egg-info/PKG-INFO
ceexample.egg-info/SOURCES.txt
ceexample.egg-info/dependency_links.txt
ceexample.egg-info/entry_points.txt
ceexample.egg-info/top_level.txt