Metadata-Version: 1.0
Name: ceexample
Version: 0.0.0
Summary: Celery Extension Example 
Home-page: https://github.com/yetship/ceexample
Author: yetship
Author-email: liqianglau@outlook.com
License: UNKNOWN
Platform: UNKNOWN
